calve/__init__.py
calve/main.py
calve-0.0.5.dist-info/METADATA
calve-0.0.5.dist-info/WHEEL
calve-0.0.5.dist-info/top_level.txt
calve-0.0.5.dist-info/RECORD
