Metadata-Version: 2.4
Name: calve
Version: 0.0.5
Summary: A Python-based data pipeline for ingesting, cataloging, reporting, and querying data using Apache Iceberg as the storage format and DuckDB for lightweight analytics.
Author-email: Caleb Grant <grantcaleb22@gmail.com>
Project-URL: Homepage, https://github.com/geocoug/calve
Project-URL: Repository, https://github.com/geocoug/calve
Project-URL: Issues, https://github.com/geocoug/calve/issues
Classifier: Programming Language :: Python :: 3
Classifier: Programming Language :: Python :: 3.10
Classifier: Programming Language :: Python :: 3.11
Classifier: Programming Language :: Python :: 3.12
Classifier: Programming Language :: Python :: 3.13
Requires-Python: <3.14,>=3.10
Requires-Dist: duckdb>=1.3.2
Requires-Dist: fastexcel>=0.14.0
Requires-Dist: geopandas>=1.1.1
Requires-Dist: netcdf4>=1.7.2
Requires-Dist: pandas>=2.3.1
Requires-Dist: polars>=1.31.0
Requires-Dist: pyarrow>=21.0.0
Requires-Dist: pyiceberg[glue,s3fs,sql-sqlite]>=0.9.1
Requires-Dist: pyogrio>=0.11.0
Requires-Dist: python-dotenv>=1.1.1
Requires-Dist: pyyaml>=6.0.2
Requires-Dist: rich>=13.9.4
Requires-Dist: typer>=0.16.0
Requires-Dist: xarray>=2025.6.1
Requires-Dist: xlsx2csv>=0.8.4
Requires-Dist: xlsxwriter>=3.2.5
Provides-Extra: dev
Requires-Dist: build>=1.2.2.post1; extra == "dev"
Requires-Dist: bump-my-version>=1.2.1; extra == "dev"
Requires-Dist: pre-commit>=4.2.0; extra == "dev"
Requires-Dist: pytest>=8.4.1; extra == "dev"
Requires-Dist: pytest-cov>=6.2.1; extra == "dev"
Requires-Dist: ruff==0.11.0; extra == "dev"
Requires-Dist: tox-uv>=1.26.2; extra == "dev"
Requires-Dist: twine>=6.1.0; extra == "dev"
Provides-Extra: docs
Requires-Dist: markdown-include>=0.8.1; extra == "docs"
Requires-Dist: mkdocs>=1.6.1; extra == "docs"
Requires-Dist: mkdocs-material>=9.6.16; extra == "docs"
Requires-Dist: mkdocs-mermaid2-plugin>=1.2.1; extra == "docs"
Requires-Dist: mkdocs-typer>=0.0.3; extra == "docs"
Requires-Dist: mkdocstrings[python]>=0.30.0; extra == "docs"
Requires-Dist: pymdown-extensions>=10.16.1; extra == "docs"
